abstractModel/__init__.py
abstractModel/basic_model_class.py
abstractModel-0.0.3.dist-info/LICENSE
abstractModel-0.0.3.dist-info/METADATA
abstractModel-0.0.3.dist-info/WHEEL
abstractModel-0.0.3.dist-info/top_level.txt
abstractModel-0.0.3.dist-info/RECORD
